vectra_py/__init__.py
vectra_py/item_selector.py
vectra_py/local_index.py
vectra_py-0.0.5.dist-info/LICENSE
vectra_py-0.0.5.dist-info/METADATA
vectra_py-0.0.5.dist-info/WHEEL
vectra_py-0.0.5.dist-info/top_level.txt
vectra_py-0.0.5.dist-info/RECORD
