Metadata-Version: 2.1
Name: vectra-py
Version: 0.0.5
Summary: An in memory vector index project, simliar to Pinecone DB.
Author-email: Brian Schleckser <brian.schleckser+vectrapy@gmail.com>
Project-URL: Homepage, https://github.com/BMS-geodev/vectra-py
Project-URL: Bug Tracker, https://github.com/BMS-geodev/vectra-py/issues
Classifier: Programming Language :: Python :: 3
Classifier: License :: OSI Approved :: MIT License
Classifier: Operating System :: OS Independent
Requires-Python: >=3.9
License-File: LICENSE
